{
  "Sign in": "登录",
  "Email": "电子邮件",
  "Password": "密码",
  "Two-factor authentication": "双因素认证",
  "Authentication code": "认证码",
  "Verify": "核实",
  "Sign in with SSO": "用SSO登录",
  "It seems that the authentification code is wrong.": "看来认证代码是错误的。",
  "Repeat your password": "重复你的密码",
  "Do you really want to leave without saving your changes?": "你真的想不保存你的改动就离开吗？",
  "Filename": "文件名",
  "Advanced options": "高级选项",
  "Alt": "符号",
  "Title/Caption": "标题/说明",
  "Copyright": "版权声明",
  "Something went wrong uploading some items": "在上传一些项目时出了问题",
  "Username": "帐号",
  "First name": "名字",
  "Last name": "姓氏",
  "Time zone": "时区",
  "Interface language": "界面语言",
  "New Password": "新密码",
  "New Password Confirmation": "新密码确认",
  "Phone number *": "电话号码 *",
  "Your settings have been updated!": "您的设置已被更新!",
  "Your account has been deleted.": "你的账户已被删除。",
  "Loading story": "正在加载故事",
  "Please wait a couple of seconds": "请稍等几秒钟",
  "Enabled?": "启用了吗？",
  "You need at least one column": "你至少需要一列",
  "Dimensions": "尺寸",
  "The alternates have been created!": "候补队员已经产生了!",
  "Something went wrong creating the alternates": "创建候补名单时出了问题",
  "Name": "命名",
  "Folder successfully created": "文件夹成功创建",
  "Edit": "编辑",
  "No files were found.": "没有发现任何文件。",
  "New Datasource": "新数据源",
  "Create": "创建",
  "Retry": "重试",
  "Pending": "待定",
  "Failed": "失败",
  "Success": "成功",
  "Webhook": "Webhook",
  "From": "来自",
  "To": "拟",
  "See details": "查看详情",
  "Webhook secret": "Webhook的秘密",
  "Hide": "隐藏",
  "Define/edit": "定义/编辑",
  "Story published &amp; unpublished": "故事发表&amp；未发表",
  "Story saved": "保存的故事",
  "Datasource entry saved": "保存的数据源条目",
  "Workflow changed": "工作流程改变了",
  "Release merged": "发布合并了",
  "Languages": "语言",
  "Pipeline deployed": "已部署的管道",
  "Email *": "电子邮件 *",
  "Show username instead of email as a collaborator": "显示用户名而不是电子邮件作为合作者",
  "Jane": "简",
  "Doe": "无名氏",
  "Role": "角色",
  "I am a developer or administrator": "我是一名开发人员或管理员",
  "I am a content editor": "我是一名内容编辑",
  "Choose a timezone": "选择一个时区",
  "Choose a language": "选择一种语言",
  "Default": "默认情况下",
  "Permanently delete account": "永久性地删除账户",
  "Code": "编码",
  "Cancel": "取消",
  "Send": "发送",
  "Continue with saving changes": "继续保存更改",
  "Storyblok password": "故事布洛克密码",
  "Save Changes": "保存更改",
  "Download": "下载",
  "Change password": "更改密码",
  "Password only (default)": "只有密码（默认）。",
  "Set up 2FA using Email": "使用电子邮件设置2FA",
  "Set up 2FA using SMS": "使用短信设置2FA",
  "Storyblok Management API": "Storyblok管理API",
  "Delete token": "删除标记",
  "Copy token": "抄送令牌",
  "Generate new token": "生成新令牌",
  "Token was copied to clipboard.": "令牌被复制到剪贴板上。",
  "Save": "拯救",
  "Account": "帐户",
  "Account Security": "账户安全",
  "Appearance": "外观",
  "Personal access token": "个人访问令牌",
  "Privacy": "隐私",
  "Danger zone": "危险区",
  "Please enter a valid phone number": "请输入一个有效的电话号码",
  "Logout": "登出",
  "Apps Directory": "应用目录",
  "Back to V1": "返回到V1",
  "My Spaces": "我的空间",
  "Partner Portal": "合作伙伴门户网站",
  "Apps": "应用",
  "Block Library": "块状图书馆",
  "Team": "团队",
  "Content": "内容",
  "My last edits": "我最后的编辑",
  "Unknown User": "未知用户",
  "Space actions": "空间行动",
  "Stories": "故事",
  "Assets": "资产",
  "Blocks": "块状物",
  "Users": "用户",
  "Content Activities": "内容活动",
  "Api Requests": "请求援助",
  "Check it in V1": "在V1中检查它",
  "Go to spaces": "转到空间",
  "Back to App Directory": "返回到应用程序目录",
  "Uninstall": "卸载",
  "Install": "安装",
  "Try out in trial mode": "试用模式下的试用",
  "App Directory": "应用程序目录",
  "All": "全部",
  "Installed": "已安装",
  "My apps": "我的应用程序",
  "Copy URL": "复制网址",
  "Open the file in a new window": "在一个新的窗口中打开文件",
  "Move to folder": "移动到文件夹",
  "Replace asset": "替换资产",
  "Sync asset details": "同步资产细节",
  "Previous asset": "以前的资产",
  "Next asset": "下一个资产",
  "Asset URL copied with success": "成功复制了资产URL",
  "Alt text": "Alt文本",
  "Tags": "标签",
  "Choose existing or add new": "选择现有的或添加新的",
  "Expiration date": "过期日期",
  "Source": "来源",
  "Overview": "概述",
  "References": "参考文献",
  "Metadata": "元数据",
  "Activity": "活动",
  "Asset metadata is coming soon!": "资产元数据即将到来!",
  "Asset activity is coming soon!": "资产活动很快就会到来!",
  "Open document": "打开文件",
  "Insufficient permissions": "许可证不充分",
  "Search folders...": "搜索文件夹...",
  "Add content folder": "添加内容文件夹",
  "Sort": "分类",
  "Creation date (asc)": "创建日期（升）",
  "Creation date (desc)": "创建日期 (desc)",
  "Update date (asc)": "更新日期（升）",
  "Update date (desc)": "更新日期 (desc)",
  "Name (asc)": "名称（升）",
  "Name (desc)": "名称（描述）",
  "Move": "移动",
  "Folders updated": "文件夹更新",
  "Assets updated": "资产更新",
  "Public": "公众",
  "Add more": "添加更多",
  "Upload": "上传",
  "Back": "溯源",
  "Start adding your files": "开始添加你的文件",
  "Drag and drop any file": "拖放任何文件",
  "Insert": "插入",
  "API Url": "API Url",
  "Export": "出口",
  "Import": "进口",
  "Discard changes": "丢弃变化",
  "Discard": "弃置",
  "Back to datasources": "返回到数据源",
  "Autosave": "自动保存",
  "Settings": "设置",
  "Value": "价值",
  "Add": "添加",
  "Search by name...": "按名称搜索...",
  "No entry found": "没有找到条目",
  "Are you sure?": "你确定吗？",
  "Delete": "删除",
  "Datasource entry removed successfully": "数据源条目成功删除",
  "Search datasources": "搜索数据源",
  "By Name (asc)": "按姓名 (升)",
  "By Name (desc)": "按姓名(描述)",
  "By Creation Date (asc)": "按创建日期（升）计算",
  "By Creation Date (desc)": "按创建日期（描述）划分",
  "By Updated Date (asc)": "按更新日期（升）计算",
  "By Updated Date (desc)": "按更新日期(desc)计算",
  "Datasource removed successfully": "数据源成功删除",
  "Datasources": "数据来源",
  "No datasources found": "没有找到数据源",
  "No datasources in this space at the moment.": "目前在这个空间没有数据源。",
  "Your trial period has expired": "你的试用期已经过了",
  "View plans": "查看计划",
  "Name of the new space *": "新空间的名称 *",
  "Do you want to assign the space to your organization?": "你想把空间分配给你的组织吗？",
  "Yes (visible to everyone in the organization)": "是的（对组织中的每个人都可见）。",
  "Duplicate space": "重复的空间",
  "Spaces": "空间",
  "Add Space": "添加空间",
  "Search spaces...": "搜索空间...",
  "No results found": "没有发现结果",
  "Last updated": "最后更新",
  "By name": "按姓名",
  "Search the entire repository": "搜索整个资源库",
  "By name (asc)": "按姓名(升)",
  "By name (desc)": "按名称(desc)",
  "By last update (asc)": "通过最后一次更新（升）。",
  "By last update (desc)": "按最后一次更新(desc)计算",
  "Back to root content directory": "返回到根内容目录",
  "Homepage": "主页",
  "Type something...": "输入一些东西...",
  "Enabled ?": "已启用？",
  "Select date": "选择日期",
  "Options": "选择",
  "Option": "选项",
  "Remove entire filter": "删除整个过滤器",
  "Done": "已完成",
  "Search...": "搜索...",
  "Deploy from source": "从源头部署",
  "Deploy": "部署",
  "Open pipelines settings": "打开管道设置",
  "Open preview": "公开预览",
  "e.g. Winter special": "例如：冬季特别",
  "Choose": "选择",
  "Pipeline to deploy": "部署的管道",
  "Publish now": "现在发布",
  "Content type": "内容类型",
  "Last update": "最后更新",
  "Author": "作者",
  "Insert block": "插入块",
  "All blocks": "所有区块",
  "Content Conflict": "内容冲突",
  "Copy over": "复制过来",
  "Overwrite": "覆盖",
  "Back to Spaces": "返回到空间",
  "We have a few questions that our marketing team wants to know": "我们有几个问题是我们的营销团队想知道的",
  "Role *": "角色 *",
  "Acme Company": "橡树公司",
  "Job function *": "工作职能 *",
  "Business area *": "业务领域 *",
  "Continue": "继续",
  "Privacy Policy": "隐私政策",
  "Please fill out all the required fields": "请填写所有必填项",
  "here": "这里",
  "The command was successfully copied to clipboard": "该命令已成功复制到剪贴板上",
  "All systems operational": "所有系统运行",
  "These settings are coming soon!": "这些设置很快就会出现!",
  "Delete Access Token": "删除访问令牌",
  "Token successfully deleted!": "代币成功删除!",
  "Key": "钥匙",
  "Access level": "访问级别",
  "Pipeline": "管道",
  "Choose pipeline": "选择管道",
  "Optional": "可选",
  "Token successfully copied": "令牌复制成功",
  "Item saved successfully!": "项目成功保存!",
  "Learn more": "了解更多",
  "Generate": "生成",
  "Token": "代币",
  "List of paths to invalidate": "要废止的路径列表",
  "Invalidate": "无效",
  "The invalidation process has been initiated": "无效程序已经启动",
  "Please type the space name to proceed": "请键入空间名称以继续进行",
  "Delete this space": "删除这个空间",
  "Select language to add": "选择要添加的语言",
  "Enable publish translations individually": "启用单独发布翻译",
  "Name of the default language": "默认语言的名称",
  "Enter the language code": "输入语言代码",
  "Name of this language": "该语言的名称",
  "I am sure": "我确信",
  "Preview url": "预览网址",
  "Source of sync": "同步的来源",
  "Delete pipeline": "删除管线",
  "The pipeline has been updated successfully!": "该管道已成功更新!",
  "Edit pipeline": "编辑管线",
  "Remove pipeline": "移除管线",
  "The pipelines have been updated successfully!": "管线已成功更新!",
  "Pipeline created successfully!": "管线创建成功!",
  "Space Name": "空间名称",
  "Space ID": "空间标识",
  "Default content type": "默认的内容类型",
  "Introducing a new Storyblok Pricing.": "介绍一个新的Storyblok定价。",
  "contact us.": "联系我们。",
  "learn more": "了解更多",
  "Contact us.": "联系我们。",
  "Monthly Billing": "月度帐单",
  "Annual Billing (One month off)": "年度计费（减免一个月）",
  "Ok": "好的",
  "Payment successful!": "付款成功!",
  "Subscribe": "订阅",
  "Current plan": "目前的计划",
  "Location (default environment)": "位置（默认环境）",
  "Mobile width in px": "手机宽度，单位：px",
  "Tablet width in px": "平板电脑的宽度，单位为px",
  "Disable Visual Editor": "禁用视觉编辑器",
  "Close": "关闭",
  "Choose webhook": "选择webhook",
  "Slack Webhook Hook": "Slack Webhook挂钩",
  "Task Triggered Hook": "任务触发的钩子",
  "Pipeline deployed Hook": "管道部署挂钩",
  "Story Published Hook": "故事发表 钩子",
  "Stage Changed Hook": "阶段性改变的钩子",
  "Datasource Entry Saved Hook": "数据源输入保存的钩子",
  "Release Merged Hook": "释放合并的钩子",
  "Story Saved Hook": "故事拯救了钩子",
  "Status": "状况",
  "No webhook logs found with these filters.": "没有发现有这些过滤器的webhook日志。",
  "No webhook logs at the moment.": "目前没有webhook日志。",
  "Failed to retry send to webhook": "重试向webhook发送失败",
  "Webhook success": "Webhook成功",
  "View logs": "查看日志",
  "Color": "颜色",
  "Stage Name": "舞台名称",
  "Workflow stage created!": "工作流程阶段已经创建!",
  "Workflow deleted successfully!": "工作流程成功删除!",
  "Define as default stage for new content items": "定义为新内容项目的默认阶段",
  "Right to publish and schedule content": "发布和安排内容的权利",
  "Administrators": "管理员",
  "All users": "所有用户",
  "All stages": "所有阶段",
  "Specific stages": "具体阶段",
  "Try search in all content items": "尝试在所有内容项目中进行搜索",
  "Create new content": "创建新的内容",
  "Search blocks...": "搜索区块...",
  "Search blocks": "搜索区块",
  "Hide Content Navigator": "隐藏内容导航器",
  "Resolve": "决心",
  "Original field was removed": "原有领域被删除",
  "edit": "编辑",
  "replace": "替换",
  "delete": "删除",
  "Clear Clipboard": "透明剪贴板",
  "Select all": "选择所有",
  "copy": "拷贝",
  "Choose date": "选择日期",
  "Define the anchor id of the link": "定义链接的锚点ID",
  "Anchor id": "锚的ID",
  "Clear story selection": "清晰的故事选择",
  "Choose an option": "选择一个选项",
  "Code Block Language": "代码块语言",
  "Choose language": "选择语言",
  "Select language": "选择语言",
  "JavaScript": "脚本",
  "Bash": "巴什",
  "Ruby": "茹比",
  "Plaintext": "明文",
  "HTML": "HTML",
  "Markdown": "标记",
  "Paste your markdown here": "将你的标记粘贴在这里",
  "You need at least one row": "你需要至少有一行",
  "Edit table": "编辑表",
  "Edit field": "编辑领域",
  "Translate": "翻译",
  "Link": "链接",
  "Select a Target": "选择一个目标",
  "Get started": "开始吧",
  "Schedule a demo": "安排一个演示",
  "Save and show": "保存和显示",
  "Can I build a full blown website with Storyblok?": "我可以用Storyblok建立一个完整的网站吗？",
  "What is the Storyblok bridge?": "什么是Storyblok桥？",
  "Can I create a blog with Storyblok?": "我可以用Storyblok创建一个博客吗？",
  "How does Storyblok work?": "Storyblok是如何工作的？",
  "Preview url could not be set.": "预览网址无法设置。",
  "Preview URLs": "预览网址",
  "Add or change preview urls": "添加或更改预览尿液",
  "Edit preview URLs": "编辑预览URL",
  "Responsive view": "响应式视图",
  "Merge the changes to the selected story": "将修改合并到所选故事中",
  "Merge the changes into all connected stories.": "将这些变化合并到所有相连的故事中。",
  "Read documentation": "阅读文件",
  "Browse content folders": "浏览内容文件夹",
  "The alternate(s) have been merged!": "候补者已经被合并了!",
  "Stories merged successfully.": "故事合并成功。",
  "Alternate story created with success": "成功创建的另一个故事",
  "Story was overwritten.": "故事被写滥了。",
  "Learn more about Internationalization": "了解更多关于国际化的信息",
  "Publish all": "发布所有",
  "More": "更多",
  "Preview": "预览",
  "Restore": "恢复",
  "Restore this version?": "恢复这个版本？",
  "No changes for the selected version": "选择的版本没有变化",
  "Version restored": "版本恢复",
  "Edit mode": "编辑模式",
  "Visual": "视觉",
  "Define as root for the folder": "定义为文件夹的根",
  "Sort by date": "按日期排序",
  "First published date": "首次出版日期",
  "Real path": "真实路径",
  "Shortcut": "捷径",
  "Pin as shortcut in the my content browser": "在我的内容浏览器中，将其作为快捷方式钉住",
  "Story updated": "故事更新",
  "Story was not updated": "故事没有更新",
  "Back to content list": "返回到内容列表",
  "Story fields exports successfully": "故事字段成功导出",
  "Choose XML or JSON file": "选择XML或JSON文件",
  "The story is not updated": "该故事没有更新",
  "Workflow stage": "工作流程阶段",
  "Assign to": "指派给",
  "Select a person": "选择一个人",
  "Roles": "角色",
  "Select a role": "选择一个角色",
  "Delete workflow stage": "删除工作流程阶段",
  "Workflow updated successfully!": "工作流程更新成功!",
  "Workflow stages sorted successfully!": "工作流程阶段成功排序!",
  "Settings Tab": "设置选项卡",
  "Space": "空间",
  "Subscription": "订阅",
  "Visual Editor": "视觉编辑",
  "Internationalization": "国际化",
  "Webhooks": "网络钩子",
  "Webhook Logs": "Webhook日志",
  "Access Tokens": "访问令牌",
  "Workflow": "工作流程",
  "Asset Library": "资产库",
  "Rendered": "渲染的",
  "Backup": "备份",
  "Search": "搜索",
  "Pipelines": "管道",
  "Maintenance mode": "维护模式",
  "Danger Zone": "危险区",
  "Settings updated successfully!": "设置更新成功!",
  "Take the Tour": "游览",
  "You are in an example space. Anytime you feel ready you can start your own space.": "你是在一个范例空间。任何时候你觉得准备好了，你可以开始你自己的空间。",
  "Create a new space": "创造一个新的空间",
  "The maintenance mode is enabled. Only admins can edit content.": "维护模式已启用。只有管理员可以编辑内容。",
  "This space could not be loaded.": "这个空间无法加载。",
  "Custom comment": "自定义评论",
  "Add a comment": "添加评论",
  "Remove custom comment": "删除自定义注释",
  "Add a custom comment": "添加一个自定义的评论",
  "Notify users via email": "通过电子邮件通知用户",
  "Comments": "评论",
  "History": "历史",
  "No comments yet": "尚无评论",
  "Show older comments": "显示较早的评论",
  "Coming Soon!": "即将推出!",
  "Workflow stages could not be loaded": "无法加载工作流阶段",
  "Comments could not be loaded": "评论无法加载",
  "No changes were made to the workflow": "没有对工作流程进行修改",
  "Error sending message to iframe": "向iframe发送消息时出错",
  "Story saved and scheduled!": "故事已经保存并安排好了!",
  "Story saved!": "故事得救了!",
  "Could not overwrite content": "无法重写内容",
  "Story unpublished": "未发表的故事",
  "Story was not unpublished": "故事不是未发表的",
  "Changes discarded": "弃用的变化",
  "Changes were not discarded": "更改没有被丢弃",
  "Remove": "移除",
  "Completed": "已完成",
  "View": "查看",
  "Open": "开放式",
  "Back to Courses": "回到课程",
  "Topic": "主题",
  "Level": "级别",
  "Go Back": "返回首页",
  "Learning": "学习",
  "Team Management": "团队管理",
  "Finances": "财务",
  "Perks": "奖励",
  "Company Settings": "公司设置",
  "General": "一般",
  "OAuth 2": "OAuth 2",
  "App Details": "应用详情",
  "Delete App": "删除应用程序",
  "Install Link": "安装链接",
  "Copy Link": "复制链接",
  "ID": "身份证",
  "Slug": "鼻涕虫",
  "Client ID": "客户ID",
  "Client Secret": "客户秘密",
  "URL to your app": "你的应用程序的URL",
  "OAuth2 callback URL": "OAuth2回调URL",
  "Website": "网站",
  "URL to a website": "一个网站的URL",
  "Your name": "你的名字",
  "Short Description": "简要说明",
  "Short description what the app is about": "简要描述该应用程序的内容",
  "URL to a Youtube video": "Youtube视频的URL",
  "Video": "视频",
  "Long Description": "长篇描述",
  "Screenshot": "屏幕截图",
  "Icon": "图标",
  "Sidebar Icon": "侧边栏图标",
  "General Settings": "一般设置",
  "App was updated": "应用程序已更新",
  "App was deleted": "应用程序被删除",
  "App": "应用",
  "App ID": "应用ID",
  "Type": "类型",
  "Edited": "已编辑",
  "Name of the app": "应用程序的名称",
  "App type": "应用类型",
  "Sidebar": "侧边栏",
  "Sidebar Apps are located in the space sidebar.": "侧边栏应用程序位于空间侧边栏中。",
  "Tool": "工具",
  "Tool apps are located inside the story editor.": "工具应用程序位于故事编辑器内。",
  "New App": "新的应用程序",
  "Search Apps...": "搜索应用程序...",
  "Create a new app": "创建一个新的应用程序",
  "App was created": "应用程序已创建",
  "Publish": "发布",
  "Input": "输入",
  "Choose a space": "选择一个空间",
  "key": "钥匙",
  "value": "价值",
  "Add Option": "添加选项",
  "Output": "输出",
  "Assigned Spaces": "指定空间",
  "Documentation": "文件",
  "Local Development Mode": "地方发展模式",
  "Examples": "实例",
  "FAQ": "常见问题",
  "Previous version restored": "恢复了以前的版本",
  "Amount": "数量",
  "Connect Stripe": "连接条纹",
  "Invoices": "发票",
  "Select a period": "选择一个时期",
  "all": "所有",
  "today": "今天",
  "Past 7 days": "过去7天",
  "Past 30 days": "过去30天",
  "Past 90 days": "过去90天",
  "Past year": "过去一年",
  "Reset Search": "重置搜索",
  "Last Updated Spaces": "最后更新的空间",
  "Master Storyblok Partner Program": "故事会大师合作伙伴计划",
  "Storyblok Partner Program Documents": "Storyblok合作伙伴计划文件",
  "View Documents": "查看文件",
  "Need Help?": "需要帮助吗？",
  "Partner Support": "合作伙伴支持",
  "Previous": "上一篇",
  "Next": "下一页",
  "Complete missing lessons first": "先完成缺失的课程",
  "Complete Course": "完整的课程",
  "Back to Dashboard": "回到仪表板",
  "View Courses": "查看课程",
  "Start this course": "开始这个课程",
  "Reset Course Progress": "重置课程进度",
  "Partner Resources": "合作伙伴资源",
  "Start a Storyblok course or browse the partner documents": "开始一个Storyblok课程或浏览合作伙伴文件",
  "Logo": "徽标",
  "Action": "行动",
  "Get Perk": "获得津贴",
  "Search perks ...": "搜索福利...",
  "Company*": "公司*",
  "Company (can be changed later)": "公司（以后可以更改）",
  "Website (optional)": "网站（可选）",
  "Country*": "国家*",
  "Country": "国家",
  "Street*": "街头*",
  "ZIP*": "兹*",
  "City": "城市",
  "Billing Mail Address": "账单邮寄地址",
  "Company Number": "公司编号",
  "Bank information (for revenue share of enterprise plans)": "银行信息（用于企业计划的收入分成）。",
  "VAT number": "增值税号",
  "Settings were updated": "设置已更新",
  "Project Name": "项目名称",
  "Plan": "计划",
  "Choose to": "请选择",
  "Add an exisiting space": "增加一个现有的空间",
  "My New Space": "我的新空间",
  "Partner Spaces": "伙伴空间",
  "New Space": "新空间",
  "Choose a role": "选择一个角色",
  "Member": "会员",
  "Owner": "业主",
  "Add Member": "添加会员",
  "User was updated": "用户被更新",
  "The user was removed from the partner portal.": "该用户已从合作伙伴门户中删除。",
  "View Roadmap": "查看路线图",
  "Add comment": "添加评论",
  "Filetypes": "文件类型",
  "Default assets folder": "默认的资产文件夹",
  "Choose...": "选择...",
  "Allowed maximum": "允许的最大值",
  "Default value": "默认值",
  "Allow only specific components to be inserted": "只允许插入特定的组件",
  "Component(s)": "组成部分(s)",
  "Group(s)": "集团(s)",
  "Component whitelist": "组件白名单",
  "Component group whitelist": "组件组白名单",
  "Custom Type": "自定义类型",
  "Required field(s) (comma separated)": "必填项（逗号分隔）。",
  "Disable time selection": "禁用时间选择",
  "Prepend https to url": "将https预置到url中",
  "Force crop": "力量作物",
  "Keep original size": "保持原始尺寸",
  "Enable RTL": "启用RTL",
  "Allow empty paragraphs": "允许空段落",
  "Customize toolbar items": "定制工具条项目",
  "Maximum characters": "最大字符数",
  "Enable email field": "启用电子邮件字段",
  "Enable asset selection": "启用资产选择",
  "Enable anchor field on internal link": "启用内部链接的锚字段",
  "Restrict to content types": "限制于内容类型",
  "Content type whitelist": "内容类型白名单",
  "Force folder restriction": "强制文件夹限制",
  "Restrict to folder": "限制在文件夹中",
  "Exclude from export": "排除在出口之外",
  "It will be not sent or exported to the JSON.": "它将不会被发送或导出到JSON。",
  "Min value": "最小值",
  "Max value": "最大值",
  "Number of decimals": "小数点的数量",
  "Number of steps": "步骤数",
  "Select a source": "选择一个来源",
  "Add options": "添加选项",
  "Hide empty option": "隐藏空选项",
  "Use UID instead of ID": "使用UID而不是ID",
  "Path to folder of stories": "故事文件夹的路径",
  "Restrict to content type": "限制于内容类型",
  "Internal datasource": "内部数据源",
  "URL": "URL",
  "Minimum": "最低限度",
  "Maximum": "最大",
  "Self": "自己",
  "Datasource": "数据来源",
  "External JSON": "外部JSON",
  "Custom CSS class": "自定义CSS类",
  "Choose components": "选择组件",
  "Choose groups": "选择组别",
  "Regex validation": "Regex验证",
  "Description": "描述",
  "Force overwrite by merge action": "通过合并动作强制覆盖",
  "Required field": "必须填写",
  "Translatable": "可翻译的",
  "Select block type": "选择区块类型",
  "Content type block": "内容类型块",
  "Nested block": "嵌套块",
  "Universal block": "通用块",
  "Filter": "过滤器",
  "Block icon": "块状图标",
  "Use default": "使用默认值",
  "Display name": "显示名称",
  "Preview field": "预览领域",
  "Select the field for preview": "选择要预览的领域",
  "Preview template": "预览模板",
  "Read the documentation": "阅读文件",
  "Preview screenshot": "预览屏幕截图",
  "New tab name": "新标签名称",
  "Delete preset": "删除预设",
  "Field type": "字段类型",
  "Name of the new attribute": "新属性的名称",
  "Manage tabs": "管理标签",
  "Delete option": "删除选项",
  "Filter field types": "过滤字段类型",
  "Fields": "领域",
  "Config": "配置",
  "Start by adding field types": "从添加字段类型开始",
  "Add Block": "添加区块",
  "All Blocks": "所有区块",
  "Choose parent folder": "选择父文件夹",
  "Duplicate": "重复的",
  "Title": "标题",
  "Click to load and start video": "点击加载并启动视频",
  "youtube video": "视频",
  "e.g. Landing": "例如：登陆",
  "Parent folder": "父文件夹",
  "None": "无",
  "Choose existing": "选择现有的",
  "Add new": "添加新的",
  "Choose content type": "选择内容类型",
  "Name of content type": "内容类型的名称",
  "Folder content settings": "文件夹内容设置",
  "Deny changing content type": "拒绝改变内容类型",
  "Disable visual composer": "禁用视觉合成器",
  "Create your new space": "创造你的新空间",
  "Create space": "创造空间",
  "Contact your space owner": "联系你的空间所有者",
  "My account": "我的账户",
  "Upload asset": "上传资产",
  "Select a stage": "选择一个阶段",
  "+ Add new preset": "+ 添加新的预设",
  "Delete Preset": "删除预设",
  "Create Your Account": "创建您的账户",
  "Enter your email": "输入你的电子邮件",
  "Your password must be at least 8 characters long": "你的密码必须至少有8个字符",
  "Please check that the passwords match": "请检查密码是否匹配",
  "I agree to the ": "我同意",
  "Terms of Service": "服务条款",
  " and ": "和",
  "Sign up": "报名参加",
  "Already signed up?": "已经报名了吗？",
  "Password requirements": "密码要求",
  "At least 8 characters": "至少8个字符",
  "At least 1 lowercase character": "至少有1个小写字符",
  "At least 1 uppercase character": "至少1个大写字母的字符",
  "At least 1 number": "至少有1个数字",
  "At least 1 special character": "至少有1个特殊字符",
  "Please check that the passwords match.": "请检查密码是否匹配。",
  "Please agree to our Terms of Service and Privacy Policy": "请同意我们的服务条款和隐私政策",
  "Are you sure that you want to delete items listed below?": "你确定要删除下面列出的项目吗？",
  "Select all (Include associated alternates)": "选择所有（包括相关的候补）。",
  "There are": "有",
  "reference(s)": "参考文献(s)",
  "deleted successfully": "成功删除",
  "items": "项目",
  "folder": "文件夹",
  "story": "故事",
  "Item has been duplicated": "项目已被重复使用",
  "Items has been duplicated": "项目被重复了",
  "Preset": "预设",
  "Start typing to search": "开始打字进行搜索",
  "Save changes": "保存更改",
  "All published stories will be available to the public.": "所有发表的故事都将向公众开放。",
  "item": "项目",
  "The": "ǞǞǞ",
  "Copy the URL of the image": "复制图片的URL",
  "Copy Url": "复制网址",
  "Could not load assets": "无法加载资产",
  "Are you sure you want to move": "你确定你要搬家吗？",
  "Translated name": "翻译的名字",
  "Translation updated!": "译文更新了!",
  "Enter your password": "输入你的密码",
  "Sign in with email": "用电子邮件登录",
  "Tell us more about your business": "告诉我们更多关于您的业务",
  "Competencies *": "能力 *",
  "Company size *": "公司规模 *",
  "How long have you been using Storyblok *": "您使用Storyblok有多久了 *？",
  "Do you have an immediate customer opportunity? *": "你有即时的客户机会吗？*",
  "Yes": "是",
  "No": "没有",
  "Partner Agreement": "合作伙伴协议",
  "Please fill all the required fields": "请填写所有必填项",
  "Account Information": "帐户信息",
  "Company name *": "公司名称 *",
  "Acme Corporation": "橡树公司",
  "Country *": "国家 *",
  "Select a country": "选择一个国家",
  "Street *": "街道 *",
  "The street needs to be a minimum of 4 characters.": "街道需要至少有4个字符。",
  "Your Street 42": "你的42号街",
  "ZIP *": "ZIP *",
  "Your ZIP code": "您的邮政编码",
  "City *": "市 *",
  "Your city": "你的城市",
  "Continue to next step": "继续下一步骤",
  "Tax number": "税号",
  "Provide your tax number, e.g. 12-3456789": "提供你的税号，如12-3456789",
  "Join the Storyblok Partner Program": "加入Storyblok合作伙伴计划",
  "The Storyblok Partner Program is free to join.": "Storyblok合作伙伴计划是免费加入的。",
  "Specifies the interval between numbers in the input field.": "指定输入字段中数字的间隔时间。",
  "Block Group": "区块组",
  "Select a group": "选择一个组",
  "Technical name *": "技术名称 *",
  "Preset name": "预设名称",
  "e.g. Variant 1": "例如：变体1",
  "Fill preset with current content": "用当前内容填充预设",
  "e.g. With CTA": "例如：有CTA",
  "Add preset": "添加预设",
  "Search block groups...": "搜索街区组...",
  "Search results": "搜索结果",
  "Block groups": "块状群体",
  "+ New Group": "+ 新集团",
  "Duplicating blocks": "复制区块",
  "Duplicating block": "复制块",
  "Save folder name": "保存文件夹名称",
  "Group": "集团",
  "Actions": "行动",
  "Move to Group": "转移到集团",
  "Universal": "通用",
  "Content Type": "内容类型",
  "Nested": "嵌套",
  "Move block": "移动块",
  "Search all blocks": "搜索所有区块",
  "By last update (newest)": "按最后一次更新（最新）计算",
  "By last update (oldest)": "按最后一次更新（最古老）计算",
  "Block library": "块状图书馆",
  "New Block": "新区块",
  "Group empty": "集团空",
  "This block does not exist.": "这个区块不存在。",
  "Block(s) successfully moved!": "块成功移动!",
  "Group successfully deleted!": "集团成功删除!",
  "Assign a workflow stage": "指定一个工作流程阶段",
  "Show": "显示",
  "Content updates": "内容更新",
  "Asset updates": "资产更新",
  "Activities": "活动",
  "Rename": "重命名",
  "No search results": "没有搜索结果",
  "All results": "所有结果",
  "Replace": "替换",
  "You cannot move a": "你不能移动一个",
  "folder to the same folder": "文件夹到同一个文件夹",
  "root folder to a child folder": "根文件夹到一个子文件夹",
  "Folders": "文件夹",
  "Select All": "选择所有",
  "Clear": "清楚",
  "Selected": "精选",
  "Delete asset": "删除资产",
  "Delete folder": "删除文件夹",
  "The asset was successfully replaced": "该资产被成功替换",
  "The folder was successfully deleted": "该文件夹已成功删除",
  "The folder could not be deleted": "该文件夹无法被删除",
  "The asset was successfully deleted": "该资产已成功删除",
  "The asset could not be deleted": "该资产不能被删除",
  "Unpublish": "取消出版",
  "Asset Folder Permissions": "资产文件夹权限",
  "Add asset folders to restrict editing and upload access.": "添加资产文件夹以限制编辑和上传权限。",
  "All asset folders": "所有资产文件夹",
  "Allow access to Block Library": "允许访问块状图书馆",
  "Blocks/content type permissions": "区块/内容类型权限",
  "All block/content types": "所有块/内容类型",
  "Blocks field permissions": "阻断字段权限",
  "Add block fields here to hide them in the interface.": "在这里添加块状字段，以在界面中隐藏它们。",
  "Show hidden first": "先显示隐藏的",
  "Hidden": "隐藏的",
  "All languages": "所有语言",
  "All pipelines": "所有管线",
  "Folder/Content item permissions": "文件夹/内容项的权限",
  "All folders/content items": "所有文件夹/内容项目",
  "Datasource permissions": "数据源权限",
  "All datasources": "所有数据源",
  "Unselect all": "取消选择所有",
  "External id (Used for SSO)": "外部ID（用于SSO）。",
  "Content & Editor": "内容和编辑",
  "Allow reading content": "允许阅读的内容",
  "Allow saving content": "允许保存内容",
  "Allow publishing content": "允许发布内容",
  "Allow unpublishing content": "允许取消发布内容",
  "Allow deploying pipelines": "允许部署管道",
  "Allow deleting content": "允许删除内容",
  "Deny access to image editor": "拒绝访问图像编辑器",
  "Deny access to visual editor": "拒绝对视觉编辑器的访问",
  "Deny changing alternates group": "拒绝改变候补成员组",
  "Deny moving a story": "拒绝搬动一个故事",
  "Deny changing the slug of a story": "拒绝改变一个故事的线索",
  "Force user to use a release": "强制用户使用释放",
  "Hide content if unauthorized": "如果未经授权，隐藏内容",
  "Hide folders if unauthorized": "如果未经授权，隐藏文件夹",
  "Allow managing tags": "允许管理标签",
  "Allow editing datasource values": "允许编辑数据源值",
  "Allow editing datasource keys": "允许编辑数据源键",
  "eCommerce app": "电子商务应用",
  "Allow access to ecommerce app": "允许访问电子商务应用程序",
  "Task app": "任务应用程序",
  "Allow access to the tasks app": "允许访问任务应用程序",
  "Define role access rights.": "定义角色访问权限。",
  "Role name": "角色名称",
  "Permissions": "许可权",
  "user": "用户",
  "You need to provide a role name.": "你需要提供一个角色名称。",
  "Role created successfully!": "角色创建成功!",
  "Role edited successfully!": "角色编辑成功!",
  "Default role": "默认角色",
  "Edit role": "编辑角色",
  "Remove role": "删除角色",
  "Define roles, access rights and more.": "定义角色、访问权限和更多。",
  "Learn more ": "了解更多",
  "To add custom roles, please upgrade your account.": "要添加自定义角色，请升级您的账户。",
  "Add new role": "添加新角色",
  "Can manage users and create, update projects.": "能够管理用户和创建、更新项目。",
  "Can create, update and delete content.": "可以创建、更新和删除内容。",
  "Custom roles are not included in": "自定义角色不包括在",
  "You have run out of custom roles for your current": "你已经用完了你当前的自定义角色",
  "plan, but you can try them in the": "计划，但你可以尝试在",
  "plan. You can delete  other roles, or upgrade your plan.": "计划。你可以删除其他角色，或升级你的计划。",
  "Role deleted successfully!": "角色删除成功!",
  "New Role": "新角色",
  "Edit Role": "编辑角色",
  "Provide your VAT number if you are a EU company": "如果你是一家欧盟公司，请提供你的增值税号码",
  "Delete this translation": "删除该翻译",
  "Please enter a valid e-mail": "请输入一个有效的电子邮件",
  "Please check if the password matches the requirements.": "请检查密码是否符合要求。",
  "Choose the folder/content items": "选择文件夹/内容项目",
  "Clear selection": "清除选择",
  "Loading more...": "载入更多...",
  "Add a name and choose the field type you want in this block.": "添加一个名称并选择你想在这个区块中使用的字段类型。",
  "Create new block": "创建新区块",
  "Presets": "预设",
  "Add filter": "添加过滤器",
  "Remove all filters": "删除所有过滤器",
  "Add filters": "添加过滤器",
  "Upload photo": "上传照片",
  "Recommended: 500px x 500px (JPG or PNG)": "推荐。500px x 500px (JPG或PNG)",
  "Please enter a valid username": "请输入一个有效的用户名",
  "Please select one of the roles": "请选择其中一个角色",
  "Time zone and language preferences": "时区和语言偏好",
  "Private asset": "私人资产",
  "Make asset private": "使资产私有化",
  "Schedule asset publishing to public": "向公众发布资产的时间表",
  "Make the asset public at a specific time automatically.": "让资产在特定时间自动公开。",
  "Please select a future date": "请选择一个未来的日期",
  "Remove focus point": "移除聚焦点",
  "Click on image to add focus point": "点击图片，添加聚焦点",
  "Delete Asset": "删除资产",
  "Close Asset Details": "关闭资产详情",
  "Size": "尺寸",
  "File": "文件",
  "in": "在",
  "Private Asset": "私人资产",
  "not scheduled": "未安排",
  "Schedule publish date": "安排发布日期",
  "Schedule": "时间表",
  "Scheduled:": "已安排。",
  "Save & Next": "保存和下一步",
  "Search assets...": "搜索资产...",
  "Quick Filters": "快速过滤器",
  "By Alt": "作者：Alt",
  "By Title/Caption": "按标题/说明",
  "By Copyright": "版权声明",
  "Private Assets only": "仅限私人资产",
  "Error on syncing the asset information": "同步资产信息时出错",
  "Deleted content": "删除的内容",
  "Trash Bin": "垃圾桶",
  "Pipeline App installed": "已安装的管道应用程序",
  "Edit tag": "编辑标签",
  "Type a new tag name": "输入一个新的标签名称",
  "This tag name is already taken": "此标签名称已被使用",
  "Edit tag name": "编辑标签名称",
  "Remove tag": "移除标签",
  "Assigned items": "分配的项目",
  "Are you sure you want to delete these tags?": "你确定要删除这些标签吗？",
  "Are you sure you want to delete this tag?": "你确定要删除这个标签吗？",
  "Tag renamed successfully": "标签重命名成功",
  "Tags deleted successfully": "成功删除的标签",
  "New tags can be created in the config section of a content item.": "可以在内容项目的配置部分创建新标签。",
  "Search tags...": "搜索标签...",
  "No content tags": "没有内容标签",
  "Minimum Cache TTL": "最小缓存TTL",
  "Cloud name": "云名称",
  "Api Key": "Api密钥",
  "Loading... You will be redirect to Slack in a few seconds!": "正在加载...你将在几秒钟内被重新定向到Slack!",
  "Disconnect": "断开连接",
  "Are you sure you want to delete this workflow stage?": "你确定要删除这个工作流程阶段吗？",
  "Delete workflow": "删除工作流程",
  "Stage transition rules - Next available stages": "阶段转换规则 - 下一个可用的阶段",
  "Specific users/roles": "特定用户/角色",
  "Allow Editor change": "允许编辑修改",
  "Allow Admin change": "允许管理员更改",
  "Edit workflow button": "编辑工作流程按钮",
  "Delete workflow button": "删除工作流程按钮",
  "Cloudinary Integration": "Cloudinary整合",
  "Slack Integration": "斯莱克集成",
  "Server Location *": "服务器位置 *",
  "Select a server location": "选择一个服务器位置",
  "Roadmap": "路线图",
  "EU": "欧盟",
  "US": "美国",
  "Confirm": "确认",
  "All restored content will be restored to the main list.": "所有恢复的内容都将被恢复到主列表。",
  "Are you sure you want to restore": "你确定你要恢复",
  "these": "这些",
  "this": "这个",
  "Get Started": "开始吧",
  "Dashboard": "仪表板",
  "You will be able to see the private asset after you save.": "保存后，你就可以看到私人资产了。",
  "Change background color of image preview": "改变图像预览的背景颜色",
  "By deleted at (asc)": "通过删除 (asc)",
  "By deleted at (desc)": "由删除在(desc)。",
  "Deleted at": "删去了在",
  "Back to Content": "返回到内容",
  "All your deleted items will show up here.": "你所有被删除的项目将显示在这里。",
  "In order to get content in": "为了让内容在",
  "pipeline, you need to deploy it from source": "管线，你需要从源头部署它",
  "It seems you do not have any content yet.": "看来你还没有任何内容。",
  "You don’t have any deleted content": "你没有任何被删除的内容",
  "This folder is empty": "这个文件夹是空的",
  "This pipeline has never been deployed": "这条管道从未被部署过",
  "No content changes": "没有内容变化",
  "We just sent you a message with your authentication code. Enter the code in the form below to verify your identity.": "",
  "A member of our partner team will be in touch to verify your details.": "",
  "Details can be changed later in settings.": "",
  "Please select if you have an immediate customer opportunity": "",
  "I have read and agree to the ": "",
  "Please agree to the Partner Agreement": "",
  "Other": "",
  "Please enter a company name": "",
  "Please select a country": "",
  "Please enter a street with at least 4 characters": "",
  "Please enter a zip code": "",
  "Please enter a city": "",
  "Connect with Stripe": "",
  "Close Notification": "",
  "Give feedback": "",
  "The number of decimal places is the number of digits that appear after the decimal point.": "",
  "Be aware! Changing the technical name can take a few minutes to update all content items. Make sure your editors have saved their current work and exit the editor.": "",
  "Used in the JSON as block name": "",
  "Specifies a custom icon for this block to make it easier to find it": "",
  "Used in the editor interface only": "",
  "of this setting": "",
  "New tab": "",
  "You can only add new presets or edit existing ones inside the visual editor.": "",
  "Change": "",
  "Be aware! Changing the name can take a few minutes to update all content items. Make sure your editors have saved their current work and exit the editor.": "",
  "Toggle Block library": "",
  "Items": "",
  "Custom filters": "",
  "Try a different search keyword": "",
  "Story": "",
  "Folder": "",
  "A “Story” is what we call the content entries you can create in Storyblok.": "",
  "Can be used to group your entries of specific content types.": "",
  "A space is an area to manage and store content for a specific project": "",
  "Be Aware": "",
  "Unpublished stories will not be available to the public anymore.": "",
  "have been updated": "",
  "have been restored": "",
  "How can we help you?": "",
  "Report a problem": "",
  "Feature Request": "",
  "Changelog": "",
  "Community": "",
  "Pricing": "",
  "Account settings": "",
  "Help & Inspiration": "",
  "Move block top": "",
  "Move block down": "",
  "live": "",
  "Please fill out all required fields in the advanced options: ": "",
  "Set your first name so others can add you with your firstname as collaborator.": "",
  "Set your last name so others can add you with your last name as collaborator.": "",
  "Theme mode": "",
  "More theme options coming soon": "",
  "Delete Account": "",
  "Deleting your account is permant.": "",
  "Data processing agreement (DPA)": "",
  "Tokens that have been generated to access the": "",
  "Personal access tokens work like ordinary OAuth access tokens. They can be used to authenticate yourself to have full access to the managment API programmatically and should NEVER be exposed in public.": "",
  "Please copy this personal access token now. It will be visible only once.": "",
  "Live support": "",
  "Changing blocks is only allowed for admins and user roles with the \"Allow access to Block Library\" permission.": "",
  "Deleting this group will automatically unlink all blocks associated with this group.": "",
  "It seems you do not have any blocks in this group yet. You can create new or move existing blocks inside.": "",
  "Each block is a small piece of your data structure whicn can be filled with content or nested by your content editor.": "",
  "from previous 7 days": "",
  "Same as last week": "",
  "Workflows": "",
  "Plan Details": "",
  "Price": "",
  "Traffic Usage": "",
  "API Requests": "",
  "You are not allowed to access this story. Please login with an account that has access.": "",
  "Browse content": "",
  "This folders is empty": "",
  "Once you delete": "",
  "Search for content items": "",
  "Search in \"{name}\"": "",
  "Please go through the checklist below.": "",
  "Blocks you add to the content will appear here.": "",
  "Discussions": "",
  "No open discussions": "",
  "Learn more about discussions": "",
  "No resolved discussions": "",
  "Insert row": "",
  "Insert column": "",
  "Move column right": "",
  "Move column left": "",
  "Move row up": "",
  "Move row down": "",
  "Remove row": "",
  "Remove column": "",
  "Copy": "",
  "Cut": "",
  "Open in Block Library": "",
  "Open Presets": "",
  "Method 1": "",
  "Method 2": "",
  "Welcome to the Visual Editor": "",
  "Access token": "",
  "With this preview token you can connect your space to any exisiting project or demo to access your content.": "",
  "Set up preview url": "",
  "Insert the url of your local server once your project is running": "",
  "Change URL": "",
  "Not created yet": "",
  "Merge": "",
  "Create clone": "",
  "Clone to all": "",
  "Merge to all": "",
  "Dimensions are only available if you are editing a content item in a subfolder.": "",
  "Seems like you have only one folder that contains this story. Dimensions are only available if you are editing a content item in a subfolder.": "",
  "Open Draft": "",
  "Open Published": "",
  "Sync": "",
  "Draft JSON": "",
  "Published JSON": "",
  "Page History": "",
  "Undo": "",
  "Redo": "",
  "Tools": "",
  "Restart tour": "",
  "Current version": "",
  "Versions": "",
  "Changes": "",
  "The real path is the location that the editor opens if the location differs from the slug defined.": "",
  "Entry configuration": "",
  "Enable autosave": "",
  "Automatically save changes while editing content.": "",
  "Show warning notification": "",
  "Show a notification in the content to let the user know that the autosave is enabled": "",
  "Default language": "",
  "No label": "",
  "Choose XML for translation software like SDL Trados Studio or JSON for translation software like LingoHub.": "",
  "Choose a compatible XML or JSON generated from the export.": "",
  "Manage": "",
  "Page Status": "",
  "Viewing Apps Directory is only allowed for admins.": "",
  "About App": "",
  "There are no apps in this category.": "",
  "Private assets are assets that are not available to the public and can only be accessed via an access token.": "",
  "Not available to the public and can only be accessed via an access token.": "",
  "Add or remove tags": "",
  "Private asset: not available to the public and can only be accessed via an access token.": "",
  "You are currently not allowed to execute this action. Please contact the administrator of your space.": "",
  "Are you sure you want to delete these assets?": "",
  "You can activate dimensions to use datasources as translatable labels.": "",
  "All unsaved changes will be lost": "",
  "Datasource entry URL copied with success": "",
  "Datasource entries uploaded": "",
  "Are you sure you want to delete the entry": "",
  "This action cannot be undone.": "",
  "Are you sure you want to delete the datasource": "",
  "14 day trial period": "",
  "Upgrade your plan now to keep adding datasources.": "",
  "space": "",
  "The new space will be created with this name. Only content stories and blocks will be copied to the new space. Assets and users will not be copied. Assets will be referenced from the original space.": "",
  "Please provide a space name": "",
  "Starred": "",
  "Active": "",
  "Could not load spaces.": "",
  "Me": "",
  "Select...": "",
  "Content type values": "",
  "Allows you to view all items that have been deleted. Selected content items can be restored from the trash bin.": "",
  "All content that is currently on the source pipeline and the releases\n        you select.": "",
  "Releases to deploy": "",
  "No releases found in source pipeline": "",
  "Pipeline stages are read only and therefore can be used to securely deploy your content and allow your editors to change their content in a release workflow set-up.": "",
  "The deployment has been initiated": "",
  "Last deployment: ": "",
  "The deployment has been initiated and will be completed in the background": "",
  "When the release gets merged all content will be automatically deployed to the selected pipeline.": "",
  "Please enter a release name not chosen before": "",
  "Please enter a release name": "",
  "Set scheduled date": "",
  "Add Pipeline": "",
  "Add Reviewers": "",
  "Delete release": "",
  "This release will be published immediately!": "",
  "Content from this release is scheduled to be automatically published.": "",
  "Publishing it now will bring your release content changes with the current content immediately.": "",
  "Move content": "",
  "Click on the icon between rows to move your selected items to a specific position in the current list or access a folder and move the item to inside of it.": "",
  "Seems that you do not have any tags yet. You can create a new tag in the \"Entry configuration\" section of a content item.": "",
  "No Block found": "",
  "Please choose how you want to proceed. ": "",
  "It opens the newer version in a new window to let you copy over your changes.": "",
  "It overwrites the newer version with your changes.": "",
  "Quickstart": "",
  "Get started by creating and defining content structures": "",
  "We are rolling out the settings pages individually. Check back soon!": "",
  "Are you sure you want to delete the following access token": "",
  "Applications using this token will not be able to access the API anymore. The changes will be permanent and cannot be rolled back.": "",
  "Edit Access Token": "",
  "Add folders or content items the token should have access to (acts as whitelist). If no item is selected the token has rights to get all content.": "",
  "Defines the minimum of seconds for the CDN cache. The default value is 0. Setting a higher value is helpful to get a higher cache hit rate for spaces with a lot of edits or cache invalidations during a short amount of time.": "",
  "Assets upload": "",
  "If you set required fields the user will be forced to fill out those fields when uploading a new asset.": "",
  "Image service": "",
  "e.g. cloudinaryname": "",
  "e.g. 92929929929": "",
  "Deleting your space is permanent.": "",
  "Storyblok supports content in multiple languages and integrates with various tools to manage translations. These integrations support you in making your content available internationally.": "",
  "Publish translations individually": "",
  "Add languages to activate field level translations.": "",
  "Label": "",
  "Are you sure you want to delete this language? This action cannot be undone once you save these settings.": "",
  "Enable maintenance mode": "",
  "When enabled only admins can edit content": "",
  "Edit Pipeline": "",
  "Pipelines documentation": "",
  "trial period.": "",
  "Upgrade your account": "",
  "Are you sure you want to delete this pipeline?": "",
  "Add datasources the user should have access to (acts as allow list). \nIf no item is selected the user has rights to edit all datasources.": "",
  "With this role the user need to use a existing release or create one to change the content.": "",
  "Are you sure you want to delete this role?": "",
  "Slack integration": "",
  "Get notified on your Slack channel if a new Story has been published!": "",
  "With this integration you can choose a Slack channel where Storyblok posts messages whenever a user publishes new content.": "",
  "Connection failed": "",
  "Provide this ID in your support tickets": "",
  "Content Types": "",
  "You can choose the default content type. It is required to have the default content type of the space defined.": "",
  "Default Content Type": "",
  "Have questions about pricing or billing? ": "",
  "Preview urls": "",
  "Visual Editor Mode": "",
  "Executed at": "",
  "Response": "",
  "Payload": "",
  "Webhook logs": "",
  "Logs show you which requests have been sent with which payload.": "",
  "Webhook security": "",
  "All current stories that are associated to this stage will revert to the undefined stage \"None\".": "",
  "Set following stage after published": "",
  "Next available stages": "",
  "Defined stages": "",
  "Changing settings for the space is only allowed for admins.": "",
  "Learn about Dashboards": "",
  "Learn about Tags": "",
  "Image Service": "",
  "Learn about Datasources": "",
  "Learn about Activities": "",
  "Go to App Store": "",
  "Learn about Settings": "",
  "Learn about Content": "",
  "Course Completed": "",
  "Lessons": "",
  "In order to earn commissions you must connect your Stripe account": "",
  "Load more fieldtypes": "",
  "Attention! The deletion of this app will also delete all installations.": "",
  "No other versions yet.": "",
  "No invoices found": "",
  "Start Guide": "",
  "Welcome to the Partner Portal of Storyblok!": "",
  "contact our support team": "",
  "chat with partner support": "",
  "Course Finished": "",
  "contact our partner team": "",
  "Discord": "",
  "LinkedIn": "",
  "Twitter": "",
  "Created by": "",
  "Course Overview": "",
  "Please note": "",
  "more or less time": "",
  "Your progress will be saved so you can leave or resume the course at any time": "",
  "Your Stripe account is connected to Storyblok!": "",
  "Your Stripe account is not connected to Storyblok!": "",
  "Connect": "",
  "Partner Details": "",
  "development mode": "",
  "Starred Projects": "",
  "All Projects": "",
  "Loading...": "",
  "Sorry, no result found.": "",
  "Example: blogpost, product, ...": "",
  "Folder settings updated!": "",
  "Settings updated!": "",
  "Folder Settings": "",
  "New Folder": "",
  "New Content Story": "",
  "Block that can be used as content type block and nested block at same time.": "",
  "There are some changes in the {type}. Are you sure you want to save the changes?": "",
  "Story could not be loaded": "",
  "Components could not be loaded": "",
  "Storyblok needs the contact information you provide to us to contact you about our products and services that you’ve requested. For information about our privacy practices and commitment to protecting your privacy, please review our": "",
  "This email will be used to verify your partner account, send\n          you important messages, such as feature updates and breaking changes.\n          Wrong Email?": "",
  "Provide your VAT number (only for EU members), e.g. ATU999999999": "",
  "As a partner, you must have a valid Stripe account linked to your\n          Partner account to begin receiving revenue share based on the clients\n          you have brought in. It is very important to note that if you create\n          spaces before linking your Stripe account, you will not receive\n          revenue share for those spaces": "",
  "Skip, connect later": "",
  "If you select a group, the block will be added inside that block group.": "",
  "e.g. Hero, Grid, Section, Newsletter Section, Chapter, Full Width Image, Slider...": "",
  "e.g. Landing pages, Post, Authors, Product, Page, Team Members, FAQ article...": "",
  "When deleting a folder, you will also delete any stories within the folder and its sub-folders as well.": "",
  "The default server location is Europe. You can create spaces located on US server, however they will only be accessible in the V2 of Storyblok.": "",
  "When creating spaces in the US, they will not be available in the V1 of Storyblok. You might not have access to certain features that are still in the process of being implemented in the next few weeks. See our": "",
  "Set your username so others can add you as a collaborator by using your username. It has to be minimum 5 characters, can only contain letters or numbers and has to be unique. The username is optional.": "",
  "Choose how Storyblok looks to you. Select a single theme, or sync with your system and automatically switch between day and night themes.": "",
  "Have a look at our privacy policy, terms and other legal documents to know more about us. If you have any questions regarding those topics do not hesitate and chat with us using our live-chat.": "",
  "Two-factor authentication (2FA)": "",
  "Two-factor authentication adds an additional layer of security to your account by requiring more than just a password to sign in.": "",
  "Storyblok will send you an Email with a two-factor authentication code.": "",
  " Storyblok will send you a SMS with a two-factor authentication code.": "",
  "The Visual Editor enables your editors to edit their content with an in context preview, including the possibility to click on Components in their website. This feature is optional and does not depend on any specific technology.": "",
  "Create a folder structure where the first folder defines your dimension (Example: de/home, en/home).": "",
  "Sorry, the page you have requested has been deleted.": "",
  "No (for private spaces, visible only to you)": "",
  "Deleted items can not be viewed. Please, restore the item to view.": "",
  "By clicking on the number below you will be redirected to the content listing, with a custom filter to show only content with that tag.": "",
  "When enabled, all languages need to be published by going to each content item, selecting the language and clicking the Publish button.": "",
  "With this role the user will be able to access the block library, create, move, and change blocks.": "",
  "With this role the user can only read the content, save and publish buttons will be disabled.": "",
  "With this role, the user can deploy selected pipelines in the Content tab.": "",
  "With this role, the user will not have access to content that the admin or owner\n              does not allow. To select the content that the user will have access to, add the stories that the user can see in the Content tab.": "",
  "With this role, the user will not have access to content that the admin or owner\n              does not allow. To select the content that the user will have access to, add the folders that the user can see in the Content tab.": "",
  "As a partner, you must have a valid Stripe account linked to your\n            Partner account to begin receiving revenue share based on the\n            clients you have brought in. It is very important to note that if\n            you create spaces before linking your Stripe account, you will not\n            receive revenue share for those spaces": "",
  "Disabling the visual composer will let you focus on the component definition. Once you've setup the composer you can enable this option for the live-preview.": "",
  "We'll be sorry to see you go, but thanks for trying Storyblok!": "",
  "Deleting your account is permanent. All your data will be wiped out immediately and you won't be able to get it back.": "",
  "Hide Get Started. You can find it any time in the 'Help & Inspiration' menu below.": "",
  "Let's start by adding blocks": "",
  "page, no one will be able to open it, and there's no turning back.": "",
  "Make sure that you have the correct URL and the owner of the file hasn't deleted it.": "",
  "We couldn't find any assets matching your filters.": "",
  "As there are currently no changes to your content, you won't see any entry if “Show release content only” checkbox is selected.": "",
  "We couldn't find any content matching your filters.": "",
  "This folder doesn't have any content yet.": "",
  "Resize images on the fly! With Storyblok's out-of-the-box image service, you can give your customers a high-quality, compelling brand experience at a speed they wouldn't expect, no matter what device or platform they're using.": "",
  "All your data will be wiped out immediately and you won't be able to get it back.": "",
  "Limitation: The feature doesn't work yet with the \"Releases\" app and duplicating a content item will not take over the published content in other languages but we are working hard to make these last adjustments.": "",
  "You don't have pipelines yet": "",
  "This is your project's workflow. Statuses can be applied to any story in this project. You can create new statuses and customise the existing ones.": "",
  " published ": "",
  " deployed ": "",
  " updated ": "",
  " created ": "",
  " deleted ": "",
  "EU Region": "",
  "US Region": "",
  "CN Region": "",
  "in the past 14 days": "",
  "Assigned to me": "",
  "View Activities": "",
  "Last update by": "",
  "Last deployment: {date}": "",
  "Not deployed": "",
  "Search in {name}": "",
  "We couldn't find any content matching your search term {searchTerm}.": "",
  "Create new": "",
  "release overview": "",
  "Assigned to me only": "",
  "Tag": "",
  "Contains content item": "",
  "Duplicating {count} blocks": "",
  "Field name:": "",
  "+ New option": "",
  "Search for apps, discover new field types and add functionalities to your Storyblok project.": "",
  "Added languages": "",
  "This is the page that the frontend editor opens. Insert your domain/location including the protocol. Example: http://www.example.com": "",
  "Define multiple domains/locations to quickly switch the preview urls in the story-editor.": "",
  "Change default mobile and tablet responsive size of your Visual Editor": "",
  "Disable Visual Editor for this project and users will only be able to use form-only mode": "",
  "Story published & unpublished": "",
  "{count} {label} with this role": "",
  "Assigned to me ({amount})": "",
  "plan": "",
  "Your old plan will be canceled automatically.": "",
  "The {name} plan includes": "",
  "team member seats": "",
  "additional seats will be automatically charged by": "",
  "per seat / month": "",
  "Trial ended": "",
  "seat": "",
  "After this period your account will continue to run on Starter plan": "",
  "Have questions about pricing or billing?": "",
  "Your free trial has ended. You can continue to use Storyblok Starter plan": "",
  "In order to get access to more features, please subscribe.": "",
  "You can update or change your billing preferences, card info, cancel your subscription and more.": "",
  "Built to scale with any project. Choose payment interval.": "",
  "Most popular": "",
  "Thank you! You have successfully subscribed to the": "",
  "Set up a subscription": "",
  "Switch to one of our new plans": "",
  "Upgrade your plan": "",
  "Switch to {name}": "",
  "The subscription to this plan did not work at the moment.": "",
  "The subscription could not be updated at this moment.": "",
  "You are not authorized to view the billing information.": "",
  "Save as new": "",
  "Start the discussion by leaving a comment on a field or block in your content.": "",
  "This Asset is not being used.": "",
  "Used in: %{count} stories": "",
  "by": "",
  "Open image editor": "",
  "Image Editor": "",
  "Crop, rotate, resize, filter, annotate, adjust colors, and much more…": "",
  "scheduled for {publishAt}": "",
  "Private asset: not available to the public and can only be accessed via an access token. Publish date {publishDate}.": "",
  "my-field-type": "",
  "Try adjusting your search or filter to find what you're looking for.": "",
  "Field-types": "",
  "New Field-type": "",
  "Search field-types ...": "",
  "Create a new field-type": "",
  "Field-type was created": "",
  "My Plugins": "",
  "Tasks app installed": "",
  "The Tasks app lets you create tasks for editors that trigger a webhook.": "",
  "Tasks": "",
  "Paste here": "",
  "Paste copied blocks into this Space": "",
  "Navigate to any other Space and paste blocks into the Block Library": "",
  "Copy to another space": "",
  "The following blocks could not be deleted": "",
  "Field-type Preview": "",
  "Settings & Details": "",
  "Scheduled for {date}": "",
  "Not scheduled": "",
  "We couldn't find any tags matching your search term \"{searchTagsTerm}\"": "",
  "e.g. Sync job": "",
  "Task type": "",
  "Lambda Function (coming soon)": "",
  "Provide the endpoint where you want to send a POST request.": "",
  "The payload of the request contains the task and the space id.": "",
  "For example: {\"task\": {\"id\": 1, \"name\": \"Sync job\"}, \"space_id\": 12345}`": "",
  "User dialog": "",
  "User dialog is a dialog which pops up when the user wants to execute the task.": "",
  "Learn more.": "",
  "Remove Task": "",
  "New Task": "",
  "Edit Task": "",
  "Task saved successfully": "",
  "Never": "",
  "Execute task": "",
  "Edit task": "",
  "Remove task": "",
  "Execute": "",
  "Task name": "",
  "Last Execution": "",
  "Are you sure you want to execute {task} task?": "",
  "Task executed successfully": "",
  "We couldn't find any tasks matching your search term \"{searchTasksTerm}\"": "",
  "Create Task": "",
  "Search tasks...": "",
  "Are you sure you want to delete this task?": "",
  "The Tasks app is a simple way to trigger a build for production or other common use-cases like product syncs or other publishing tasks.": "",
  "No tasks": "",
  "Task deleted successfully": "",
  "The language {langName} is already added": "",
  "You'll not be billed yet. All transactions are secure and encrypted by": "",
  "Subscribe to Storyblok {plan}": "",
  "Continue to checkout": "",
  "external user": "",
  "disabled user": "",
  "Edit user": "",
  "Disable user": "",
  "Enable user": "",
  "My Organization": "",
  "Can be added to organization spaces": "",
  "Can manage organization users, spaces and account settings": "",
  "Normal": "",
  "SSO@Salesforce": "",
  "Salesforce ID": "",
  "Provide the 15 digit ID": "",
  "Is sandbox user?": "",
  "New User": "",
  "Disabling the user": "",
  "We couldn't find any users matching your search term.": "",
  "You don't have any users yet.": "",
  "Add user": "",
  "All Users": "",
  "Internal Users": "",
  "SSO Users": "",
  "External Users": "",
  "Disabled Users": "",
  "Disable": "",
  "No users found": "",
  "No users": "",
  "Organization Details": "",
  "Traffic": "",
  "Organization": "",
  "View Spaces": "",
  "View Finances": "",
  "Check out these helpful resources to get you started.": "",
  "Content could not be loaded": "",
  "Restore asset": "",
  "View Details": "",
  "Open Image Editor": "",
  "Back to Assets": "",
  "Deleted Assets": "",
  "Permanently delete all": "",
  "Restore assets": "",
  "Upload files": "",
  "You don’t have any deleted assets": "",
  "Restore item(s)": "",
  "Yes, Delete": "",
  "Assets will be gone forever and you won’t be able to restore it.": "",
  "The asset(s) was/were successfully restored": "",
  "The asset(s) could not be restored": "",
  "The assets were successfully permanently deleted": "",
  "The assets could not be permanently deleted": "",
  "You are not allowed to manage tasks. Please contact your space admin.": "",
  "You don't have access to this space. Please contact the space owner.": "",
  "Created": "",
  "Storyblok": "",
  "After adding the selected Space to {name}, it will automatically be fitted into your current plan.": "",
  "Add space to organization": "",
  "Manage users": "",
  "Space settings": "",
  "Remove from organization": "",
  "There are no spaces in your organization yet.": "",
  "You are not part of any organization spaces.": "",
  "Are you sure that you want to remove this space from the organization?": "",
  "Organization Spaces": "",
  "Could not remove the space from the organization.": "",
  "Admin": "",
  "Can manage organization users, spaces": "",
  "Usertype": "",
  "Please enter a valid email address": "",
  "Firstname": "",
  "Lastname": "",
  "This will keep this user from accessing organization spaces": "",
  "Recently updated spaces": "",
  "View All": "",
  "It seems you do not have any field-types yet": "",
  "No logs found": "",
  "It seems you do not have any apps yet": "",
  "It seems you do not have any spaces yet": "",
  "{icon} Datasources are not included in this {plan}, but you can try them in the {period}.": "",
  "Please enter a valid email": "",
  "Please enter a valid email address.": "",
  "Will be used as our primary contact information to you. Others will be able to add you as collaborator by providing the full email address.": "",
  "Names for plugins need to be unique so they can be used across different spaces.": "",
  "Special characters and spaces are not allowed and the name needs to be unique.": "",
  "Revenue": "",
  "MRR": "",
  "Active subscriptions": "",
  "Number of Spaces": "",
  "Welcome 👋": "",
  "Field-types can be selected as custom type inside the component schema.": "",
  "Please enter a valid name/n": "",
  "Please select an app type/n": "",
  "Please enter a valid slug": "",
  "Edited {date}": "",
  "Fieldtype": "",
  "Select the Field-types that you would like to include in this app.": "",
  "Do you really want to delete this app?": "",
  "Please upload a square image": "",
  "Change image": "",
  "Delete image": "",
  "Please upload an image": "",
  "Development": "",
  "Square, white transparent ": "",
  "Target Folder": "",
  "seats": "",
  "Please upload an image with a minimum width of {minWidth}px": "",
  "Live": "",
  "ID / Slug": "",
  "Invoice ID": "",
  "Please enter a space name": "",
  "Please select a space.": "",
  "Invitation": "",
  "User": "",
  " - Can manage spaces and apps": "",
  " - Can manage users, spaces, apps, partner account settings and see finances": "",
  "Edit Team Member": "",
  "Add Team Member": "",
  "Field-type(s)": "",
  "Search {label}": "",
  "Default Course Icon": "",
  "View PDF": "",
  "Courses": "",
  "Documents": "",
  "Stripe Connect": "",
  "Connect your Stripe account to receive your revenue share each month.": "",
  "Once you remove this user, they will no longer have access to the Partner Portal": "",
  "Options (key/value)": "",
  "Enable Local Development Mode": "",
  "If you assign this plugin to a space other developers can also use it in the schema definition. If the plugin is not assigned to a space, it will be only available to you.": "",
  "Attention: All spaces using this field-type will not be able to use it any longer if you click delete.": "",
  "Field-type Documentation": "",
  "In progress: {percentage}%": "",
  "In Progress: {percentage}%": "",
  "We couldn't find any content matching your search term '{term}'.": "",
  "Get 1TB monthly traffic usage and additional features like shared components, scheduling and more.": "",
  "Compare plans": "",
  "updates": "",
  "requests": "",
  "api requests": "",
  "Block Field Options": "",
  "Select a field-type plugin": "",
  "Date/Time Field Options": "",
  "File Field Options": "",
  "Width ({width})": "",
  "Height ({height})": "",
  "Image Field Options": "",
  "Markdown Field Options": "",
  "Writing starts from the right of the page and continues to the left.": "",
  "Rich-text as default": "",
  "Multi-Assets Field Options": "",
  "Link Field Options": "",
  "Example: categories/": "",
  "With {level} the path will be replaced dynamically using parts of the current slug. Examples: {0}/categories/, {0}/{1}/categories/": "",
  "Number Field Options": "",
  "Recommended to be checked, as UID is required for automatic link resolving.": "",
  "In case you have a multi-language folder structure you can add the {0} placeholder and the path will be adapted dynamically. Examples: {0}/categories/, {0}/{1}/categories/": "",
  "Plugin Options": "",
  "Multi-Options Field Options": "",
  "Single-Option Field Options": "",
  "Richtext Field Options": "",
  "Text Field Options": "",
  "Defines if the field can be translated using the field level translations feature. Enable this feature by adding languages in the space settings area.": "",
  "+ Upload": "",
  "Choose a field type": "",
  "Text": "",
  "Examples: news_items, body, columns, title, description or call_to_action_btn, ...": "",
  "e.g. news_items, title, columns...": "",
  "Save & Back to Fields": "",
  "All Groups": "",
  "In order to duplicate them, set a new name for the following duplicates since a block name must be unique:": "",
  "Move {blocks} blocks": "",
  "Searching in group '{group}'": "",
  "Nestable": "",
  "The following blocks could not be {actionType}": "",
  "mo": "",
  "{currency}{price}{decimal}00": "",
  "Are you sure you want to delete the preset": "",
  "Please define a name for each added tab or delete it": "",
  "Block created successfully": "",
  "Learn more about field types": "",
  "Add a new tab and use it to group fields as an alternative to the group field type.": "",
  "You can only add new presets or edit existing ones on the active editor block \"{component}\".": "",
  "Remove as Default": "",
  "Mark as Default": "",
  "Define the new name of {component}": "",
  "Navigate to another Space": "",
  "Show release content only": "",
  "Public access tokens are only for accessing the published version while preview tokens are for accessing the draft version. Both are read-only tokens.": "",
  "Select an Access": "",
  "Asset": "",
  "Theme": "",
  "Are you sure you want to delete the space": "",
  "Min 2 and Max 8 Characters": "",
  "Your preview url must contain http:// or https://": "",
  "Pipeline name e.g Staging, Live": "",
  "Editor": "",
  "Space ID successfully copied": "",
  "Stripe": "",
  "Your account is subscribed to an old Storyblok plan, and it won't\n          change unless you decide to switch to one of our new plans. Learn more\n          in our article": "",
  "If you have any questions or feedback, feel free to": "",
  "Current Plan:": "",
  "Billing preferences/Invoices": "",
  "Name (e.g. Live, Dev)": "",
  "Location (e.g. http://www.yoursite.com)": "",
  "Ensure your server is only receiving the expected Storyblok requests for security reasons.": "",
  "e.g. http://www.your-site.com/clear_cache": "",
  "Webhooks allow you to send Storyblok activity to external services and custom integrations.": "",
  "Drafting, Reviewing...": "",
  "This color is not valid. Please insert a valid Hex code.": "",
  "Back to {parentPage}": "",
  "Plan: {name}": "",
  "{number} block(s) successfully {actionType}!": "",
  "No search results in '{parent}'": "",
  "Edited {date} by {author}": "",
  "Delete '{name}' space": "",
  "{users} of {maxCollaborators} {seatsLabel}": "",
  "* Additional seats will be automatically charged {currency}{price} per seat / {interval}": "",
  "{price} per month": "",
  "To open the app with the development urls append ?dev=1 to the url. Example: app.storyblok.com/#!/me/spaces/1/apps/1/detail?dev=1": "",
  "Minimum 1000px": "",
  "File format: png, jpg": "",
  "Square 1024 x 1024px": "",
  "File format: png, jpg or svg": "",
  "File format: svg": "",
  "A data source is simply a collection of key-value pairs (KVP). <br>Key-value pairs can be used for a single choice, multiple choice options and as well directly through our API to use them for multi-language labels, categories, or anything similar.": "",
  "We couldn’t find a datasource with the name {name}": "",
  "{num} preset | {num} presets": "",
  "{num} block deleted! | {num} blocks deleted!": "",
  "Tip: use Ctrl + S to save": "",
  "Edit token": "",
  "Delete tab button": "",
  "Added pipelines {amount}": "",
  "With Storyblok's pipeline, stages define a strict content staging workflow in your space. This is crucial if you want to create a reliable production environment. You can define multiple stages, each with its own API access token for your content, to preview and test before it goes live. Check out our {pipeline} for details.": "",
  "Pipelines are not included in {currentPlan} plan, but you can try them in the {trial}.": "",
  "trial period": "",
  "Add to Slack": "",
  "Remove preview URL": "",
  "Mobile width": "",
  "Tablet width": "",
  "Users/Roles who can change the stage {name} to the next available stage": "",
  "Do you want to learn about the Editor?": "",
  "Our Visual Editor is what makes Storyblok unique. Take a quick tour of the Editor to learn about the most important functionalities.": "",
  "<img class=\"introjs-welcome-step-img\" src=\"https://a.storyblok.com/f/88751/980x252/3afa7600d5/introjs-welcome.png\" /> <div class=\"introjs-welcome-step-h\">Make things happen with Storyblok Visual Editor</div>": "",
  "Edit and manage your content easier than ever before! You can take a quick product tour and check all the new stuff that we added.": "",
  "Visual editor toggle": "",
  "You can easily switch between the form only and the visual mode.": "",
  "Block navigator": "",
  "With the new block navigator, you can search and browse your content blocks.": "",
  "You can create comments on every content field and see an overview of the resolved and the unresolved discussions.": "",
  "Content browser": "",
  "The content browser allows quick access to your content items.": "",
  "The block library now includes an overview of all available blocks.": "",
  "Leave a Feedback": "",
  "Your feedback helps us create the best possible customer experience. Please fill our Storyblok v2 survey.": "",
  "Skip tour": "",
  "The Visual Editor shows a preview of your page and allows you to click and live-edit different components. <a href=\"https://www.storyblok.com/docs/Guides/storyblok-latest-js\" target=\"_blank\" class=\"text-teal\">Learn more</a>": "",
  "In the \"Content View\" you can edit the content blocks of your Story.": "",
  "In the \"Discussion View\" you will see active comments on this Story. <a href=\"https://www.storyblok.com/docs/guide/in-depth/content-authoring#commenting\" target=\"_blank\" class=\"text-teal\">Learn more</a>": "",
  "Entry Configuration": "",
  "In the \"Entry Configuration\" you can edit all the important settings for your Story, like changing the slug, adding tags of setting a publishing date. <a href=\"https://www.storyblok.com/docs/schema-configuration\" target=\"_blank\" class=\"text-teal\">Learn more</a>": "",
  "Toggle View": "",
  "The \"Toggle View\" allows you to switch between the Visual Editor and the Form Only editing": "",
  "Breakpoints": "",
  "The \"Breakpoints Option\" allows you to preview your changes on different breakpoints: mobile, tablet, desktop.": "",
  "The Editor functionality can be enhanced with App functionality. <a href=\"https://www.storyblok.com/docs/plugins/introduction\" target=\"_blank\" class=\"text-teal\">Learn more</a>": "",
  "The \"Options Area\" allows you to jump between different drafts of this Story.": "",
  "The \"Preview Button\" allows you to preview your page outside of Storyblok.": "",
  "The \"Save Button\" saves your current changes as a draft version.": "",
  "The \"Status Circle\" shows you the current status of the Story: draft, saved or published.": "",
  "Publish Button": "",
  "The \"Publish Button\" allows you to publish your changes.": "",
  "Publish Menu": "",
  "The \"Publish Menu\" has additional features: looking at the JSON output of the draft or published versions of your Story. <a href=\"https://www.storyblok.com/docs/guide/essentials/accessing-data\" target=\"_blank\" class=\"text-teal\">Learn more</a>": "",
  "Content Browser": "",
  "The \"Content Browser\" allows you to quickly jump to different stories without leaving the Editor.": "",
  "Back Navigation": "",
  "By clicking the \"Back Icon\" you can return to your space.": "",
  "Let's get started by opening our first story. Click on the home story.": "",
  "You can create new entries and folders by using this button.": "",
  "Do you want to learn about Spaces?": "",
  "What is a Space? Think of it as a place to keep all the content related to one project. Each space has its own components, datasources, assets, environments, domains, collaborator and permissions.": "",
  "Under \"Help & Inspiration\" you can contact our support or restart this onboarding tutorial.": "",
  "Please upload an image of the format: {filetypes}": "",
  "Allowed characters are letters, numbers and dashes.": "",
  "For additional help, {support} or {chat}": "",
  "or {signInEmail}": "",
  "Don't have an account? {signUp}": "",
  "{resend} confirmation email": "",
  "Welcome back": "",
  " Sign in to Storyblok": "",
  "Re-send the code": "",
  "Resend": "",
  "We just sent you a message with your authentication code.": "",
  "New code sent": "",
  "The verification link expires after 2 weeks. If you don't verify your email within 2 weeks, you can request another email verification link.": "",
  "Resend confirmation": "",
  "Enter your email address": "",
  "Back to login": "",
  "Story was not {errorType}": "",
  "name": "",
  "0 days left | 1 day left | {n} days left": "",
  "Save & Close": "",
  "trashbin": "",
  "Asset successfully updated": "",
  "Select Asset": "",
  "Tiles": "",
  "Change to tiles view": "",
  "List": "",
  "Change to list view": "",
  "All Folders": "",
  "to {name}": "",
  "to...": "",
  "{n} item | {n} items": "",
  "Move {item} {to}": "",
  "were not updated": "",
  "Edit before upload {file}/{total}": "",
  "or upload from your computer.": "",
  "Are you sure you want to delete the folder '{folder}'?": "",
  "Are you sure you want to restore {asset}? | Are you sure you want to restore these assets?": "",
  "Permanently delete {number} item? | Permanently delete {number} items?": "",
  "Are you sure you want to delete the asset '{name}'?": "",
  "{n} item selected | {n} items selected": "",
  "Name (e.g German)": "",
  "Value (e.g de-at)": "",
  "Delete datasource": "",
  "Shared block library": "",
  "Learn more about shared block library": "",
  "View Blocks": "",
  "This space uses shared blocks from the '{name}' space.": "",
  "This space uses shared blocks from the space #{id}.": "",
  "You are not allowed to manage the block library": "",
  "Block added to clipboard": "",
  "Remove the last copied item": "",
  "Paste from Clipboard History": "",
  "Paste from clipboard": "",
  "Paste ": "",
  "Ops, the component was not found": "",
  "Tool options": "",
  "Clear history": "",
  "View App details": "",
  "Copy to clipboard": "",
  "Remove from clipboard": "",
  "Your clipboard is empty": "",
  "{value} in clipboard": "",
  "Shared components": "",
  "Shared components allow you to share blocks across spaces by setting up a 'parent space'. Parent spaces can have multiple 'child spaces'. After adding the parent space ID, all block definitions will be inherited from the parent space. You need to have admin rights on that space.": "",
  "Please use an ID from a different Space": "",
  "Parent Space ID": "",
  "e.g. 123": "",
  "friend@example.com, otherfriend@example.com, ...": "",
  "per {interval}": "",
  "{num} user | {num} users": "",
  "Add the blocks or content types the user should not be able to select (acts as a block list). If no item is selected the user has rights to add all blocks or content types": "",
  "Add languages the user should have access to (acts as allow list). If no item is selected the user has rights to edit all content.": "",
  "Add pipelines the user should have the right to deploy to (acts as allow list). If no item is selected the user has rights to deploy to all pipelines.": "",
  "Add folders or content items the user should have access to (acts as allow list). If no item is selected the user has rights to edit all content.": "",
  "Page not found": "",
  "Access denied": "",
  "The page you are looking for does not exist.": "",
  "Created {date}": "",
  "Default theme": "",
  "Current month": "",
  "Space usage": "",
  "Traffic usage": "",
  "API requests": "",
  "Content types": "",
  "Preview environments": "",
  "Number of assets": "",
  "Users/seats maximum": "",
  "Custom roles": "",
  "of traffic usage in the past {monthLabel}": "",
  "Back to Organization Spaces": "",
  "Organization space": "",
  "Free trial expired": "",
  "Select an existing space": "",
  "Organization Spaces with access": "",
  "Organization Spaces without access": "",
  "Add a custom logo": "",
  "Provide the full url to the logo like: https://www.example.com/editor/logo.svg": "",
  "Please enter a valid url": "",
  "Add Url": "",
  "Url to the editor": "",
  "Please provide a valid url": "",
  "https://www.example.com/editor/": "",
  "Provide the full url like: https://www.example.com/editor/": "",
  "Sidebar logo": "",
  "Add your own logo and give Storyblok dashboard a personal touch": "",
  "Custom": "",
  "Set Logo Url": "",
  "Best image sizes: 250px x 40px SVG, PNG with transparent background": "",
  "Organization name": "",
  "Street": "",
  "Zip": "",
  "Please enter the SSO url you want to add (Example: https://xyz--storyblok.xyz.visual.force.com/apex/StoryblokAdmin)": "",
  "SSO URL": "",
  "https://INSERT_YOUR_SSO_URL": "",
  "Organizations Settings Tab": "",
  "SSO Settings": "",
  "Customize": "",
  "Logo Url": "",
  "friend@example.com": "",
  "Recently added users": "",
  "Images": "",
  "Videos": "",
  "Audio": "",
  "Text-Documents": "",
  "Any filetype": "",
  "Delete field button": "",
  "Deleting tab <span>'{nameDeleteTab}'</span> will not delete schema fields inside of it. All fields will be moved to the General tab.": "",
  "Add new tab": "",
  "default toggle button": "",
  "Delete preset button": "",
  "Field Type": "",
  "Field Name": "",
  "Command + S": "",
  "Control + S": "",
  "Open manage tabs": "",
  "You don't have authorization to view this page.": "",
  "Make some changes": "",
  "Remove Get Started": "",
  "Sit tight, we`re creating your space.": "",
  "3 of 3": "",
  "2 of 2": "",
  "Your example space": "",
  "Sign in with different account": "",
  "Close content browser": "",
  "All Content": "",
  "published": "",
  "saved": "",
  "Field-type was {message}": "",
  "Do you really want to delete this field-type?": "",
  "No activities found.": "",
  "Icon {name}": "",
  "Could not load apps": "",
  "Could not load app categories": "",
  "S3-Bucket and AWS-ARN": "",
  "Backups content (stories) and blocks": "",
  "Backup now": "",
  "Edit backup": "",
  "Daily backup at: {date}": "",
  "S3-bucket: {bucket}   ·   AWS-ARN: {arn}": "",
  "The backup has been created": "",
  "Define your S3-Bucket and AWS-ARN": "",
  "Backups content (stories) and components": "",
  "Activate automatic daily backups": "",
  "S3-bucket": "",
  "my-bucket": "",
  "Define the name of the S3-bucket where you want to store your backups.": "",
  "AWS Role ARN": "",
  "Back to filled data": "",
  "Need help with backup setup?": "",
  "Link to Show setup instructions": "",
  "Show setup instructions": "",
  "Backup setup instructions": "",
  "1. Read the tutorial on {tutorial}": "",
  "how to setup an Amazon IAM role": "",
  "2. Create an Amazon IAM role with following access policy document": "",
  "The role should have the permission to access and create files on the S3 bucket you defined. You can for example use the following permission policy replacing YOUR_BUCKET with your bucket name:": "",
  "Creates a new space with the restore date in the space name": "",
  "Overwrite the existing space and you will loose all existing data.\n            The process can take minutes to hours depending on the number of content items in the backup.": "",
  "Restore spaces from backups on your Amazon S3 bucket.": "",
  "Path to backup file": "",
  "Select entities to restore": "",
  "Restore destination": "",
  "Restore now": "",
  "Component definitions": "",
  "Installed apps": "",
  "Collaborators and roles": "",
  "New space": "",
  "Overwrite current space": "",
  "Restore, Overwrite": "",
  "Are you sure you want to overwrite?": "",
  "Are you sure you want to restore?": "",
  "Use your Amazon S3 bucket to create backups.": "",
  "You'll be automatically charged for the subscription once you click Subscribe": "",
  "Let's talk": "",
  "Contact us": "",
  "You have too many collaborators to subscribe to this plan.": "",
  "Contact Us": "",
  "Built for Enterprises with scalability, security and an enterprise-grade feature set in mind": "",
  "Backup & Restore": "",
  "Disable maintenance mode": "",
  "Background task running {label}": "",
  "Open story actions": "",
  "See Content Errors list": "",
  "Sorry, there are missing values.": "",
  "Close Content Errors list": "",
  "Toggle Block Navigator": "",
  "Hide all": "",
  "Expand all": "",
  "+{num} more reply | +{num} more replies": "",
  "Update": "",
  "Post": "",
  "Reply": "",
  "Write a comment and notify others with @": "",
  "Once you delete the {labelDiscussion}, there’s no turning back.": "",
  "Resolved Discussion": "",
  "Discussion": "",
  "comment": "",
  "discussion": "",
  "The discussion does not exist in this language.": "",
  "Comment was deleted from discussion!": "",
  "Discussion was deleted!": "",
  "Discussion was resolved!": "",
  "Discussion was edited!": "",
  "Comment was added to the discussion!": "",
  "Discussion was created!": "",
  "Field {title}": "",
  "Default Language": "",
  "Resolved": "",
  "Add description...": "",
  "+ Add {type}": "",
  "<strong>{num}</strong> block in clipboard | <strong>{num}</strong> blocks in clipboard": "",
  "Paste {quantity} block | Paste {quantity} blocks": "",
  "Paragraph": "",
  "Bold": "",
  "Italic": "",
  "Inline Code": "",
  "Code block": "",
  "Unordered List": "",
  "Ordered List": "",
  "Quote": "",
  "Horizontal rule": "",
  "Picture": "",
  "Help": "",
  "Toggle Richtext": "",
  "Headline 1": "",
  "Headline 2": "",
  "Headline 3": "",
  "Headline 4": "",
  "Headline 5": "",
  "Headline 6": "",
  "+ Add Assets": "",
  "+ Add Asset": "",
  "Anchor id of the link:": "",
  "Internal link": "",
  "Url": "",
  "Please insert a valid email address": "",
  "Please insert a valid URL": "",
  "The options could not be loaded.": "",
  "The stories could not be loaded.": "",
  "Strike": "",
  "Underline": "",
  "Paste from Markdown": "",
  "Custom CSS": "",
  "Default language {defaultLang}": "",
  "Add default language content": "",
  "Open in Google translate": "",
  "Hide default language": "",
  "Show default language": "",
  "See the discussion": "",
  "Start a discussion": "",
  "This block has no fields, you can define the fields in Block Library": "",
  "Define block fields": "",
  "No fields are defined for this block": "",
  "Define": "",
  "Your block consists of one or multiple fields with different field types. The field type defines what kind of content you want your editors to be able to store. You can choose from many different types.": "",
  "Current window": "",
  "New window": "",
  "Last saved: {date}": "",
  "http:// is not allowed": "",
  "Please follow instructions below on how to setup https://": "",
  "Start a development server with https proxy:": "",
  "// Install mkcert for creating a valid certificate (Mac OS):": "",
  "// Then install and run the proxy": "",
  "{toCopyLabel} successfully copied": "",
  "Command": "",
  "Show form view": "",
  "Show visual editor": "",
  "Overwrite the existing story in the folder with the current story": "",
  "Use the current story to generate a duplicate in the /{name}": "",
  "Current story:": "",
  "Duplicate the current story into all available folders.": "",
  "more options": "",
  "Discarding changes...": "",
  "Unpublishing...": "",
  "Open Content Browser": "",
  "Switch to visual mode": "",
  "Switch to form-only mode": "",
  "Search {searchName}...": "",
  "Next to content browser": "",
  "Overlay content browser": "",
  "Locked": "",
  "Save & Schedule": "",
  "Edit release": "",
  "Schedule release": "",
  "Please create a preview token, that is not associated to a branch.": "",
  "Please create a preview token for this pipeline to access the JSON for this pipeline.": "",
  "Close overlay": "",
  "1 update by {author}": "",
  "No changes made by {author}": "",
  "{num} updates by {autor}": "",
  "You’re editing content in the {name} release.": "",
  "Once you edit and click “Save & Schedule” your changes will be added to release automatically.": "",
  "Allows you to use the slug of the folder for the current Story. Example /posts for an overview instead of /posts/overview.": "",
  "Allows sorting by date using sort_by=sort_by_date as parameter.": "",
  "{appName} tool is coming soon!": "",
  "Close Tools": "",
  "Install your first tool": "",
  "No tools installed on this space": "",
  "View app store": "",
  "Block deleted": "",
  "Comments will be sent with the notification email if you choose to notify the users": "",
  "All custom comments added on workflow changes will appear here.": "",
  "We will notify you once this feature is ready.": "",
  "Save workflow stage": "",
  "{user} is currently editing content, once saved you’ll be able to continue with editing.": "",
  "Every content change you make will be automatically saved.": "",
  "Auto save enabled": "",
  "Error sending message to iframe on action {action}": "",
  "Story published {inAllLanguages}": "",
  "in all languages": "",
  "scheduled": "",
  "Saving failed. Please check if you filled out all fields correctly.": "",
  "Content locked": "",
  "Resolved ({num})": "",
  "Open ({num})": "",
  "Sorry, no results found.": "",
  "Maximum number of characters exceeded \\n({num} characters entered, {toLimit} characters remaining)": "",
  "// https is now running on port 3010 and forwarding requests to http": "",
  "14 days trial period ends on {date}": "",
  "Built with scalability, security and enterprise-grade feature set in mind": "",
  "Inline-code": "",
  "Code-block": "",
  "Unordered list": "",
  "Ordered list": "",
  "Image": "",
  "Strikethrough": "",
  "Components": "",
  "Paste Markdown": "",
  "Textarea": "",
  "Richtext": "",
  "Number": "",
  "Date/Time": "",
  "Boolean": "",
  "Multi-Options": "",
  "Single-Option": "",
  "Multi-Assets": "",
  "Table": "",
  "Commerce": "",
  "Image (old)": "",
  "File (old)": "",
  "Plugin": "",
  "Includes 30 team member seats": "",
  "For businesses with highest security & scalability standards": "",
  "Contact us today to learn how Storyblok can provide an ROI for your business": "",
  "Enterprise": "",
  "Enterprise Plus": "",
  "Select datetime option": "",
  "from": "",
  "to": "",
  "is": "",
  "after": "",
  "before": "",
  "between": "",
  "Duplicating will create the following new blocks: <span>{blockNames}</span>.": "",
  "Duplicating will create the following new block: <span>{name}_copy</span>.": "",
  "Please insert an unique name": "",
  "Are you sure you want to delete the following {label}: <span>{blockNames}</span>? This action cannot be undone.": "",
  "Created at": "",
  "Updated at": "",
  "New Release": "",
  "No traffic usage": "",
  "Presets are blocks filled with the content you currently have in the selected block. The saved presets are shown for all users at the selection of new blocks.": "",
  "{num} item | {num} items": "",
  "{itemCount} in the clipboard": "",
  "If an account exists for {userEmail} you will get an email with instructions on resetting your password. If it doesn't arrive, be sure to check your spam folder or contact our support team.": "",
  "Send me instructions": "",
  "Forgot your password?": "",
  "Instructions sent!": "",
  "To reset your password, please enter the email address of your Storyblok account.": "",
  "Email with instructions successfully sent!": "",
  "Forgot password?": "",
  "Confirmation email successfully sent!": "",
  "To make it easier for the editor to find the necessary style configuration, upload a screenshot.": "",
  "users": "",
  "Add new user": "",
  "User *": "",
  "Add people by username or email address": "",
  "Invite people by username or email address": "",
  "Please enter a valid username or email": "",
  "Single role": "",
  "Multiple roles": "",
  "Choose role *": "",
  "Please select a role": "",
  "Individual permissions": "",
  "Allow managing subscription": "",
  "Delete user": "",
  "Send invite": "",
  "The collaborator has been added to the space.": "",
  "The collaborator has been updated successfully.": "",
  "Transferring the ownership will make you an Admin user, and you will not be able to undo these changes once transfer is done.": "",
  "Transfer space ownership": "",
  "Email of new owner": "",
  "Enter a different email, the email above belongs to the current owner.": "",
  "Transfer ownership": "",
  "You need to add a valid email.": "",
  "The space owner has been updated successfully.": "",
  "We couldn't find any content matching your search term '{searchTerm}'.": "",
  "Deleted user": "",
  "Invitation expires at {date}": "",
  "Transfer ownership of the space": "",
  "Are you sure you want to remove this collaborator from this space?": "",
  "{count} seats used": "",
  "Active ({length})": "",
  "Invited ({length})": "",
  "User was successfully removed.": "",
  "No deals in this stage": "",
  "spaces": "",
  "discovery": "",
  "negotiation": "",
  "won": "",
  "lost": "",
  "Please enter an estimated start date": "",
  "Please enter an estimated launch date": "",
  "Please select the company's size": "",
  "Please add any additional information such as regarding to specific clients needs, their current technical setup, both front-end and back-end etc...": "",
  "Deal Stage": "",
  "Please select a stage": "",
  "Company Name *": "",
  "Acme Inc.": "",
  "Please enter a valid name": "",
  "Estimated Start Date *": "",
  "Select when you would like to start this project with your client.": "",
  "Select a start date": "",
  "Estimated Launch Date *": "",
  "Select when you expect to launch this project with your client.": "",
  "Select a launch date": "",
  "Preferred Storyblok Plan *": "",
  "Select the plan that your client will most likely use": "",
  "Choose a Plan": "",
  "Please select a plan": "",
  "Main contact": "",
  "Name of the clients main contact. Storyblok will not contact this person without your permission.": "",
  "John Doe": "",
  "Please enter a valid contact information": "",
  "Please select an amount of spaces": "",
  "Number of Users": "",
  "Please select an amount of users": "",
  "Company Size": "",
  "Company Website": "",
  "Please enter a valid website url": "",
  "SSO Provider": "",
  "Authentication method that enables users to securely authenticate with multiple applications and websites by just using one set of credentials.": "",
  "Please select an SSO provider": "",
  "Additional Information": "",
  "Please enter a longer description": "",
  "Delete deal": "",
  "closed": "",
  "over 500": "",
  "Discovery": "",
  "Negotiation": "",
  "Won": "",
  "Lost": "",
  "Deleting the deal with the name": "",
  "will permanently remove it from this board.": "",
  "Deals": "",
  "Add Deal": "",
  "Search deals...": "",
  "Storyblok Deals": "",
  "Add your leads for up to 10% revenue share once closed": "",
  "New Deal": "",
  "No deals found": "",
  "Add your leads for up to 10% revenue share once the deal has been won": "",
  "resolve": "",
  "cut": "",
  "Automatic": "",
  "Workflow stages": "",
  "Published & Has Changes": "",
  "Published": "",
  "Draft": "",
  "Expired": "",
  "Scheduled": "",
  "Reset Password": "",
  "To reset your password, please enter a new password below.": "",
  "Set password": "",
  "Password has been reset!": "",
  "Please check if the password and password confirmation match and that all the password requirements were filled.": "",
  "Configuration": "",
  "Misc": "",
  "{tabCaption}": "",
  "Define your business address and company information. Fields marked with * are required.": "",
  "There was a problem in loading the support chat. This might be due to some browser blocking plugins being active.": "",
  "There are some changes in the story which are not saved. Are you sure you want to discard the changes?": "",
  "Yes, discard changes": ""
}